{
  "user_id": 1332,
  "churn_probability": 99.34,
  "risk_level": "High",
  "top_features": [
    {
      "feature": "Average Screen Time",
      "value": 0.0,
      "shap_value": 3.229893922805786,
      "model": "Model A",
      "description": "Average Screen Time",
      "explanation": "\ud83d\udcca Average Screen Time: 0.0 - significantly increases churn risk"
    },
    {
      "feature": "User Tenure",
      "value": 33.0,
      "shap_value": 0.4665660262107849,
      "model": "Model A",
      "description": "How long the user has been with us",
      "explanation": "\ud83c\udfc6 Established user (33 days) - significantly increases churn risk. Long-term relationship built."
    },
    {
      "feature": "Week 3 Engagement",
      "value": 0.0,
      "shap_value": 0.37387165427207947,
      "model": "Model A",
      "description": "Activity level during their third week",
      "explanation": "\ud83d\ude34 No activity in week 3 engagement - significantly increases churn risk. User was disengaged this week."
    },
    {
      "feature": "Week 4 Engagement",
      "value": 0.0,
      "shap_value": 0.2840747535228729,
      "model": "Model A",
      "description": "Activity level during their fourth week",
      "explanation": "\ud83d\ude34 No activity in week 4 engagement - moderately increases churn risk. User was disengaged this week."
    },
    {
      "feature": "Week 3 Engagement",
      "value": 110.71,
      "shap_value": -0.2691546082496643,
      "model": "Model A",
      "description": "Activity level during their third week",
      "explanation": "\ud83c\udfaf Good activity in week 3 engagement (110 sessions) - moderately reduces churn risk."
    }
  ],
  "recommendations": [
    "We're working hard to improve. Your feedback is valuable to us!",
    "We've missed you! Check out what's new since your last visit.",
    "Explore our app's key features to enhance your daily productivity and experience."
  ],
  "chart_path": "outputs/charts/user_1332.png",
  "model_b_used": false
}