{
  "user_id": 1130,
  "churn_probability": 93.1,
  "risk_level": "High",
  "top_features": [
    {
      "feature": "User Tenure",
      "value": 16.0,
      "shap_value": -0.5519940853118896,
      "model": "Model A",
      "description": "How long the user has been with us",
      "explanation": "\ud83d\udcc8 Growing user (16 days) - significantly reduces churn risk. Still in critical onboarding period."
    },
    {
      "feature": "Week 3 Engagement",
      "value": 0.0,
      "shap_value": 0.5397204756736755,
      "model": "Model A",
      "description": "Activity level during their third week",
      "explanation": "\ud83d\ude34 No activity in week 3 engagement - significantly increases churn risk. User was disengaged this week."
    },
    {
      "feature": "Week 3 Engagement",
      "value": 0.0,
      "shap_value": 0.38014185428619385,
      "model": "Model A",
      "description": "Activity level during their third week",
      "explanation": "\ud83d\ude34 No activity in week 3 engagement - significantly increases churn risk. User was disengaged this week."
    },
    {
      "feature": "Week 5 Engagement",
      "value": 0.0,
      "shap_value": 0.3798537254333496,
      "model": "Model A",
      "description": "Activity level during their fifth week",
      "explanation": "\ud83d\ude34 No activity in week 5 engagement - significantly increases churn risk. User was disengaged this week."
    },
    {
      "feature": "Average Spent On App (Inr)",
      "value": 59.0,
      "shap_value": -0.3784891366958618,
      "model": "Model A",
      "description": "Average Spent On App (Inr)",
      "explanation": "\ud83d\udcca Average Spent On App (Inr): 59.0 - significantly reduces churn risk"
    }
  ],
  "recommendations": [
    "Discover new features in our latest update!",
    "Check out our tips & tricks section to get the most out of our app.",
    "Join our community to connect with other users and share experiences."
  ],
  "chart_path": "outputs/charts/user_1130.png",
  "model_b_used": false
}